pypiprivate/__init__.py
pypiprivate/azure.py
pypiprivate/cli.py
pypiprivate/config.py
pypiprivate/publish.py
pypiprivate/publish.py~
pypiprivate/storage.py
pypiprivate-0.5.0.dist-info/LICENSE.txt
pypiprivate-0.5.0.dist-info/METADATA
pypiprivate-0.5.0.dist-info/WHEEL
pypiprivate-0.5.0.dist-info/entry_points.txt
pypiprivate-0.5.0.dist-info/top_level.txt
pypiprivate-0.5.0.dist-info/RECORD
