Metadata-Version: 2.1
Name: pypiprivate
Version: 0.5.0
Summary: Private package management tool for Python projects
Home-page: https://github.com/helpshift/pypiprivate
Author: Vineet Naik
Author-email: vineet@helpshift.com
License: MIT License
Platform: UNKNOWN
Classifier: Environment :: Console
Classifier: Intended Audience :: Developers
Classifier: Programming Language :: Python
Classifier: Programming Language :: Python :: 2.7
Classifier: Programming Language :: Python :: 3.4
Classifier: Programming Language :: Python :: 3.6
Requires-Dist: setuptools (>=36.0.0)
Requires-Dist: Jinja2 (==2.10.0)
Requires-Dist: boto3 (==1.5.27)
Provides-Extra: azure
Requires-Dist: azure-storage-blob (==12.2.0); extra == 'azure'
